{
  "name": "Episode 24",
  "headline": "Costs of adverse events in Renal Cell Carcinoma.\n\n",
  "hosts": "Learn from the experts about the costs associated with irAEs in patients treated for Renal Cell Carcinoma. Join our hosts Dr. Afreen Shariff and Dr. Tian Zhang as they discuss with guest experts- medical Oncologists Dr. Daniel Geynisman and Dr. Bradley McGregor, MD. \n\n",
  "link_apple": "https://podcasts.apple.com/ca/podcast/episode-24-costs-of-adverse-events-in-renal-cell-carcinoma/id1541046019?i=1000632331045",
  "link_spotify": "https://open.spotify.com/episode/5ghJ25YRvX9UtgrK53aNH5?si=f54953b4385f4e4a"
}